whisper_api_sdk/__init__.py
whisper_api_sdk/api_client.py
whisper_api_sdk/api_response.py
whisper_api_sdk/configuration.py
whisper_api_sdk/exceptions.py
whisper_api_sdk/py.typed
whisper_api_sdk/rest.py
whisper_api_sdk-1.1.3.dist-info/METADATA
whisper_api_sdk-1.1.3.dist-info/WHEEL
whisper_api_sdk-1.1.3.dist-info/top_level.txt
whisper_api_sdk-1.1.3.dist-info/RECORD
