Metadata-Version: 2.4
Name: whisper_api_sdk
Version: 1.1.3
Summary: Whisper Security API
Home-page: https://github.com/whisper-sec/sdk-python
Author: Whisper Security Support
Author-email: Whisper Security Support <support@whisper.security>
Project-URL: Repository, https://github.com/GIT_USER_ID/GIT_REPO_ID
Keywords: OpenAPI,OpenAPI-Generator,Whisper Security API
Requires-Python: >=3.9
Requires-Dist: urllib3<3.0.0,>=2.1.0
Requires-Dist: python-dateutil>=2.8.2
Requires-Dist: pydantic>=2
Requires-Dist: typing-extensions>=4.7.1
Dynamic: author
Dynamic: home-page
